hmvlib/__init__.py
hmvlib/hmvcli.py
hmvlib/models.py
hmvpack_NG-0.0.3.dist-info/METADATA
hmvpack_NG-0.0.3.dist-info/WHEEL
hmvpack_NG-0.0.3.dist-info/entry_points.txt
hmvpack_NG-0.0.3.dist-info/top_level.txt
hmvpack_NG-0.0.3.dist-info/RECORD
