Metadata-Version: 2.1
Name: hmvpack-NG
Version: 0.0.3
Summary: Handling missing values in python
Home-page: https://github.com/CachingNik/HMV-Pack
Author: Nikhil Gupta
Author-email: ngupta_be17@thapar.edu
License: UNKNOWN
Keywords: CLI,missing,Data,HMV
Platform: UNKNOWN
Requires-Python: >=2.7
